[{
    "image":"img/london.jpg",
    
    "country":"London",
    "info":"this is about london. Fusce neque dolor . Suspendisse wisi qtuer."
    },
    {
    "image":"img/milan.jpg",
    
    "country":"Italy",
    "info":"this is about london. Fusce neque dolor . Suspendisse wisi qtuer."
    },{
    "image":"img/staugustine.jpg",
    
    "country":"Augustine",
    "info":"this is about london. quam. Fusce neque dolor . Suspendisse wisi qtuer."
    },{
    "image":"img/Montreal.jpg",
    
    "country":"Canada",
    "info":"this is about london. Fusce neque dolor . Suspendisse wisi qtuer."
    }]